Metadata-Version: 2.1
Name: links-verification
Version: 1.0.1
Summary: Verify that all the external/absolute links within a web page work correctly.
Home-page: UNKNOWN
Author: Dari Developer
Author-email: hernandezdarifrancisco@gmail.com
License: MIT
Project-URL: Documentation, https://github.com/DariHernandez/links_verification/blob/master/README.md
Project-URL: Funding, https://www.paypal.com/paypalme/FranciscoDari
Project-URL: Source, https://github.com/DariHernandez/links_verification
Keywords: scraping,links,verify,verify links,external links,request,bas4,beautiful soup 4,testing
Platform: UNKNOWN
Requires-Python: >=3.7
